embedded_jsonl_db_engine/__init__.py
embedded_jsonl_db_engine/blobs.py
embedded_jsonl_db_engine/database.py
embedded_jsonl_db_engine/errors.py
embedded_jsonl_db_engine/fastregex.py
embedded_jsonl_db_engine/index.py
embedded_jsonl_db_engine/init.py
embedded_jsonl_db_engine/progress.py
embedded_jsonl_db_engine/query.py
embedded_jsonl_db_engine/schema.py
embedded_jsonl_db_engine/storage.py
embedded_jsonl_db_engine/taxonomy.py
embedded_jsonl_db_engine/utils.py
embedded_jsonl_db_engine-0.1.0a7.dist-info/licenses/LICENSE
embedded_jsonl_db_engine-0.1.0a7.dist-info/METADATA
embedded_jsonl_db_engine-0.1.0a7.dist-info/WHEEL
embedded_jsonl_db_engine-0.1.0a7.dist-info/top_level.txt
embedded_jsonl_db_engine-0.1.0a7.dist-info/RECORD
