Metadata-Version: 2.4
Name: embedded_jsonl_db_engine
Version: 0.1.0a7
Summary: Embedded JSONL DB with strict schema, in-file header (schema+taxonomies), in-memory indexes, and fast regex queries.
Author: Mykola Rudenko
License: MIT
Project-URL: Homepage, https://github.com/mykolarudenko/embedded_jsonl_db_engine
Project-URL: Repository, https://github.com/mykolarudenko/embedded_jsonl_db_engine
Project-URL: Issues, https://github.com/mykolarudenko/embedded_jsonl_db_engine/issues
Keywords: jsonl,embedded,database,single-file,schema,taxonomies,regex,blobs
Classifier: Development Status :: 3 - Alpha
Classifier: Intended Audience :: Developers
Classifier: License :: OSI Approved :: MIT License
Classifier: Programming Language :: Python
Classifier: Programming Language :: Python :: 3
Classifier: Programming Language :: Python :: 3 :: Only
Classifier: Programming Language :: Python :: 3.9
Classifier: Programming Language :: Python :: 3.10
Classifier: Programming Language :: Python :: 3.11
Classifier: Programming Language :: Python :: 3.12
Classifier: Topic :: Database
Classifier: Topic :: Software Development :: Libraries
Classifier: Environment :: Console
Classifier: Operating System :: OS Independent
Requires-Python: >=3.9
License-File: LICENSE
Provides-Extra: ijson
Requires-Dist: ijson; extra == "ijson"
Provides-Extra: dev
Requires-Dist: mypy; extra == "dev"
Requires-Dist: ruff; extra == "dev"
Requires-Dist: pytest; extra == "dev"
Requires-Dist: pytest-cov; extra == "dev"
Requires-Dist: rich; extra == "dev"
Dynamic: license-file
